frontiersman/ClientMain.py
frontiersman/ClientStartWithUI.py
frontiersman/Help Doc.pdf
frontiersman/Player.py
frontiersman/README.md
frontiersman/Startup.py
frontiersman/__init__.py
frontiersman/config.txt
frontiersman/script.py
frontiersman/server.py
frontiersman/test.py
frontiersman/assets/army.png
frontiersman/assets/army_old.png
frontiersman/assets/bank.png
frontiersman/assets/bank_92x92.png
frontiersman/assets/brick_port.png
frontiersman/assets/cards.png
frontiersman/assets/city.png
frontiersman/assets/city.xcf
frontiersman/assets/city_button.png
frontiersman/assets/city_button_d.png
frontiersman/assets/city_button_h.png
frontiersman/assets/default_port.png
frontiersman/assets/dev_button.png
frontiersman/assets/dev_button_d.png
frontiersman/assets/dev_button_h.png
frontiersman/assets/end_button.png
frontiersman/assets/end_button_d.png
frontiersman/assets/end_button_h.png
frontiersman/assets/gameboard_grid.png
frontiersman/assets/gameboard_grid_v2.png
frontiersman/assets/gameboard_grid_v4.png
frontiersman/assets/gameboard_grid_v5.png
frontiersman/assets/gameboard_grid_v5_circle.png
frontiersman/assets/gameboard_grid_v6.png
frontiersman/assets/help.png
frontiersman/assets/help.txt
frontiersman/assets/num_roads.png
frontiersman/assets/ore_port.png
frontiersman/assets/port_flag_hex.png
frontiersman/assets/road.png
frontiersman/assets/road_button.png
frontiersman/assets/road_button_d.png
frontiersman/assets/road_button_h.png
frontiersman/assets/road_old.png
frontiersman/assets/settle_button.png
frontiersman/assets/settle_button_d.png
frontiersman/assets/settle_button_h.png
frontiersman/assets/settlement.png
frontiersman/assets/sheep_port.png
frontiersman/assets/star.png
frontiersman/assets/star_old.png
frontiersman/assets/trade_button.png
frontiersman/assets/trade_button_d.png
frontiersman/assets/trade_button_h.png
frontiersman/assets/wheat_port.png
frontiersman/assets/wood_port.png
frontiersman/assets/Pieces/Cities/city-blue.png
Frontiersman-2.0.2.dist-info/LICENSE
Frontiersman-2.0.2.dist-info/METADATA
Frontiersman-2.0.2.dist-info/WHEEL
Frontiersman-2.0.2.dist-info/entry_points.txt
Frontiersman-2.0.2.dist-info/top_level.txt
Frontiersman-2.0.2.dist-info/RECORD
