Metadata-Version: 2.1
Name: Frontiersman
Version: 2.0.2
Summary: Network Multiplayer Board Game
Home-page: https://gitlab.com/csi4930-frontiersman/csi4930-frontiersman
Author: Brian Snow
Author-email: snowb@ufl.edu
License: UNKNOWN
Platform: UNKNOWN
Classifier: Development Status :: 3 - Alpha
Classifier: Programming Language :: Python :: 3.8
Classifier: License :: OSI Approved :: MIT License
Classifier: Operating System :: OS Independent
Requires-Python: >=3.8
Requires-Dist: pygame (>=2.0.0.dev10)
Requires-Dist: pygame-gui
Requires-Dist: aiohttp
Requires-Dist: asyncio
Requires-Dist: requests
